setup.py
fisrt_shot/__init__.py
fisrt_shot/main.py
fisrt_shot.egg-info/PKG-INFO
fisrt_shot.egg-info/SOURCES.txt
fisrt_shot.egg-info/dependency_links.txt
fisrt_shot.egg-info/not-zip-safe
fisrt_shot.egg-info/top_level.txt
fisrt_shot/sub_1/__init__.py
fisrt_shot/sub_1/helper.py
fisrt_shot/sub_1/mod_1.py
fisrt_shot/sub_2/__init__.py
fisrt_shot/sub_2/mod_2.py